cam_ilt/__init__.py
cam_ilt/utils.py
cam_ilt/reg_inv/__init__.py
cam_ilt/reg_inv/d1.py
cam_ilt/reg_inv/d1_project.py
cam_ilt/reg_inv/d2.py
cam_ilt-0.1.0.dist-info/LICENSE
cam_ilt-0.1.0.dist-info/METADATA
cam_ilt-0.1.0.dist-info/WHEEL
cam_ilt-0.1.0.dist-info/top_level.txt
cam_ilt-0.1.0.dist-info/RECORD
