Metadata-Version: 2.1
Name: cam_ilt
Version: 0.1.0
Summary: A Python package for the inversion of magnetic resonance datasets
Home-page: https://github.com/jbbb2/cam_ilt
Author: Julian Beckmann
Author-email: jbbb2@cantab.ac.uk
Classifier: Programming Language :: Python :: 3
Classifier: License :: OSI Approved :: MIT License
Classifier: Operating System :: OS Independent
Requires-Python: >=3.9
License-File: LICENSE
Requires-Dist: numpy
Requires-Dist: scipy
